{
  "basics": {
    "name": "Sonia Mazelet",
    "image": "",
    "email": "sonia.mazelet@polytechnique.edu",
    "location": {
      "city": "Paris",
      "countryCode": "France"
    },
    "profiles": [
      {
        "network": "Twitter",
        "username": "AlbertEinstein",
        "url": "https://twitter.com/AlbertEinstein"
      }
    ]
  },
  "education": [
    {
      "institution": "École Polytechnique - Inria Saclay",
      "location": "France",
      "studyType": "PhD",
      "startDate": "2024",
      "endDate": "current"
    },
    {
      "institution": "ENS Paris-Saclay",
      "location": "France",
      "studyType": "University degree",
      "startDate": "2019",
      "endDate": "2024",
      "highlights": ["MVA master's degree (Mathematics, Vision, Learning).", "L3 and M1 in Mathematics"]
    }
  ]
}
